{"width":1080,"height":1080,"fonts":[],"pages":[{"id":"1Ly7vV0zEo","children":[{"id":"WdmCHqnyoT","type":"image","x":151.36359968644442,"y":116.70502449891444,"rotation":0,"opacity":1,"locked":false,"blurEnabled":false,"blurRadius":10,"brightnessEnabled":false,"brightness":0,"sepiaEnabled":false,"grayscaleEnabled":false,"shadowEnabled":false,"shadowBlur":5,"shadowOffsetX":0,"shadowOffsetY":0,"shadowColor":"black","width":790.4435323344286,"height":846.5899510021711,"src":"https://images.unsplash.com/photo-1564485377539-4af72d1f6a2f?crop=entropy&cs=tinysrgb&fit=max&fm=jpg&ixid=MnwxMTY5OTZ8MHwxfHNlYXJjaHwxMXx8TU9ERUx8ZW58MHx8fHwxNjIyNDQ4OTI4&ixlib=rb-1.2.1&q=80&w=1080","cropX":0,"cropY":0,"cropWidth":1,"cropHeight":0.7131406038765034,"flipX":false,"flipY":false,"borderColor":"black","borderSize":0},{"id":"Rpe-NviDa3","type":"text","x":-1.3170731707280225,"y":40.23170731707441,"rotation":0,"opacity":1,"locked":false,"blurEnabled":false,"blurRadius":10,"brightnessEnabled":false,"brightness":0,"sepiaEnabled":false,"grayscaleEnabled":false,"shadowEnabled":false,"shadowBlur":5,"shadowOffsetX":0,"shadowOffsetY":0,"shadowColor":"black","text":"TO -\nDAY","placeholder":"","fontSize":73.46589693208504,"fontFamily":"Archivo Black","fontStyle":"normal","fontWeight":"normal","textDecoration":"","fill":"rgba(253,252,252,1)","align":"center","width":317.372674808267,"height":117.54543509133612,"strokeWidth":0,"stroke":"black","lineHeight":0.8000000000000003,"letterSpacing":0},{"id":"AYDysWwzd_","type":"text","x":495.21951217512515,"y":742.2585890073036,"rotation":0,"opacity":1,"locked":false,"blurEnabled":false,"blurRadius":10,"brightnessEnabled":false,"brightness":0,"sepiaEnabled":false,"grayscaleEnabled":false,"shadowEnabled":true,"shadowBlur":41,"shadowOffsetX":0,"shadowOffsetY":0,"shadowColor":"black","text":"FLASH SALE","placeholder":"","fontSize":75,"fontFamily":"Archivo Black","fontStyle":"normal","fontWeight":"normal","textDecoration":"","fill":"rgba(253,248,248,1)","align":"center","width":537.1646347279577,"height":90,"strokeWidth":0,"stroke":"black","lineHeight":1.2,"letterSpacing":0},{"id":"XcdMdrjKCc","type":"text","x":496.34161504682584,"y":791.7594388927466,"rotation":0,"opacity":1,"locked":false,"blurEnabled":false,"blurRadius":10,"brightnessEnabled":false,"brightness":0,"sepiaEnabled":false,"grayscaleEnabled":false,"shadowEnabled":true,"shadowBlur":41,"shadowOffsetX":0,"shadowOffsetY":0,"shadowColor":"black","text":"FLASH SALE","placeholder":"","fontSize":75,"fontFamily":"Archivo Black","fontStyle":"normal","fontWeight":"normal","textDecoration":"","fill":"rgba(246,242,242,1)","align":"center","width":537.1646347279577,"height":90,"strokeWidth":0,"stroke":"black","lineHeight":1.2,"letterSpacing":0},{"id":"iU-qQCrhlc","type":"text","x":507.7769837713025,"y":837.8923800414751,"rotation":0,"opacity":1,"locked":false,"blurEnabled":false,"blurRadius":10,"brightnessEnabled":false,"brightness":0,"sepiaEnabled":false,"grayscaleEnabled":false,"shadowEnabled":true,"shadowBlur":41,"shadowOffsetX":0,"shadowOffsetY":0,"shadowColor":"black","text":"FLASH SALE","placeholder":"","fontSize":77,"fontFamily":"Archivo Black","fontStyle":"normal","fontWeight":"normal","textDecoration":"","fill":"rgba(250,246,246,1)","align":"center","width":532.6800305391126,"height":92.39999999999999,"strokeWidth":0,"stroke":"black","lineHeight":1.2,"letterSpacing":0},{"id":"nHpH9jsvGW","type":"text","x":24.120163739341077,"y":816.813773307515,"rotation":0,"opacity":1,"locked":false,"blurEnabled":false,"blurRadius":10,"brightnessEnabled":false,"brightness":0,"sepiaEnabled":false,"grayscaleEnabled":false,"shadowEnabled":false,"shadowBlur":5,"shadowOffsetX":0,"shadowOffsetY":0,"shadowColor":"black","text":"UP TO","placeholder":"","fontSize":52.48097958082666,"fontFamily":"Roboto","fontStyle":"normal","fontWeight":"normal","textDecoration":"","fill":"rgba(248,244,244,1)","align":"center","width":226.71783179756812,"height":62.97717549699199,"strokeWidth":0,"stroke":"black","lineHeight":1.2,"letterSpacing":0},{"id":"M-Xjb6RRoi","type":"text","x":-175.17073170731135,"y":848.302361056011,"rotation":0,"opacity":1,"locked":false,"blurEnabled":false,"blurRadius":10,"brightnessEnabled":false,"brightness":0,"sepiaEnabled":false,"grayscaleEnabled":false,"shadowEnabled":false,"shadowBlur":5,"shadowOffsetX":0,"shadowOffsetY":0,"shadowColor":"black","text":"25%","placeholder":"","fontSize":196.2169225061087,"fontFamily":"Abril Fatface","fontStyle":"normal","fontWeight":"normal","textDecoration":"","fill":"rgba(0,0,0,1)","align":"center","width":789.0423433728405,"height":235.4603070073304,"strokeWidth":0,"stroke":"black","lineHeight":1.2,"letterSpacing":0},{"id":"Jx72c0I9tc","type":"svg","x":1011.7222392669506,"y":3.6795814328005783,"rotation":0,"opacity":1,"locked":false,"blurEnabled":false,"blurRadius":10,"brightnessEnabled":false,"brightness":0,"sepiaEnabled":false,"grayscaleEnabled":false,"shadowEnabled":false,"shadowBlur":5,"shadowOffsetX":0,"shadowOffsetY":0,"shadowColor":"black","src":"data:image/svg+xml;base64,PHN2ZyB4bWxucz0iaHR0cDovL3d3dy53My5vcmcvMjAwMC9zdmciIHZpZXdCb3g9IjAgMCA2MCA2MCI+PHJlY3QgeD0iMCIgeT0iMCIgd2lkdGg9IjYwIiBoZWlnaHQ9IjYwIiBmaWxsPSJyZ2IoMCwgMTYxLCAyNTUpIiAvPjwvc3ZnPg==","cropX":0,"cropY":0,"cropWidth":1,"cropHeight":1,"keepRatio":false,"flipX":false,"flipY":false,"width":4.438106591328893,"height":346.3835994895575,"borderColor":"black","borderSize":0,"colorsReplace":{"rgb(0, 161, 255)":"rgba(0,0,0,1)"}},{"id":"cubZXhIDhk","type":"text","x":733.0050929329999,"y":71.08918538290979,"rotation":0,"opacity":1,"locked":false,"blurEnabled":false,"blurRadius":10,"brightnessEnabled":false,"brightness":0,"sepiaEnabled":false,"grayscaleEnabled":false,"shadowEnabled":false,"shadowBlur":5,"shadowOffsetX":0,"shadowOffsetY":0,"shadowColor":"black","text":"www.shop.com","placeholder":"","fontSize":28.846532596671054,"fontFamily":"Roboto","fontStyle":"normal","fontWeight":"normal","textDecoration":"","fill":"black","align":"center","width":219.4095412333541,"height":34.61583911600526,"strokeWidth":0,"stroke":"black","lineHeight":1.2,"letterSpacing":0}],"background":"rgba(235,144,12,1)"}]}